python_for_my_log
