Metadata-Version: 2.1
Name: python-for-my-log
Version: 0.0.10
Summary: Record your diary happily
Home-page: https://github.com/Sunxiuwen2018/sdk_python_for_mylog.git
Author: SXW
Author-email: xiuwensun@163.com
License: UNKNOWN
Platform: UNKNOWN
Classifier: Programming Language :: Python :: 3
Classifier: License :: OSI Approved :: MIT License
Classifier: Operating System :: OS Independent
Classifier: Topic :: System :: Logging
License-File: LICENSE
